shaprpy/__init__.py
shaprpy/_explain.py
shaprpy/_rutils.py
shaprpy/datasets.py
shaprpy/explanation.py
shaprpy/utils.py
shaprpy-0.4.3.dist-info/licenses/LICENSE
shaprpy-0.4.3.dist-info/licenses/LICENSE.md
shaprpy-0.4.3.dist-info/METADATA
shaprpy-0.4.3.dist-info/WHEEL
shaprpy-0.4.3.dist-info/top_level.txt
shaprpy-0.4.3.dist-info/RECORD
