Metadata-Version: 2.4
Name: shaprpy
Version: 0.4.3
Summary: Python wrapper for the R package shapr (via rpy2)
Author: Martin Jullum, Lars Henry Berge Olsen, Didrik Nielsen
License: # MIT License
Project-URL: Homepage, https://github.com/NorskRegnesentral/shapr
Project-URL: Documentation, https://norskregnesentral.github.io/shapr/shaprpy.html
Project-URL: Issues, https://github.com/NorskRegnesentral/shapr/issues
Project-URL: Changelog, https://github.com/NorskRegnesentral/shapr/blob/main/python/CHANGELOG.md
Keywords: explainable-ai,shapley-values,machine-learning,model-interpretability
Classifier: Programming Language :: Python :: 3
Classifier: Programming Language :: Python :: 3 :: Only
Classifier: Programming Language :: Python :: 3.10
Classifier: Programming Language :: Python :: 3.11
Classifier: Programming Language :: Python :: 3.12
Classifier: Programming Language :: Python :: 3.13
Classifier: License :: OSI Approved :: MIT License
Classifier: Operating System :: POSIX :: Linux
Classifier: Intended Audience :: Science/Research
Classifier: Topic :: Scientific/Engineering :: Artificial Intelligence
Requires-Python: >3.10
License-File: LICENSE
License-File: LICENSE.md
Requires-Dist: rpy2>=3.5.1
Requires-Dist: numpy>=1.22.3
Requires-Dist: pandas>=1.4.2
Requires-Dist: scikit-learn>=1.0.0
Requires-Dist: tabulate>=0.8.10
Requires-Dist: shap>=0.40.0
Requires-Dist: matplotlib>=3.5.0
Provides-Extra: test
Requires-Dist: pytest>=7.0.0; extra == "test"
Requires-Dist: syrupy>=4.0.0; extra == "test"
Requires-Dist: xgboost>=1.5.0; extra == "test"
Provides-Extra: dev
Requires-Dist: ruff>=0.1.0; extra == "dev"
Requires-Dist: pytest>=7.0.0; extra == "dev"
Requires-Dist: syrupy>=4.0.0; extra == "dev"
Requires-Dist: xgboost>=1.5.0; extra == "dev"
Dynamic: license-file
